pyrlib/__init__.py
pyrlib-0.0.1.dist-info/METADATA
pyrlib-0.0.1.dist-info/WHEEL
pyrlib-0.0.1.dist-info/top_level.txt
pyrlib-0.0.1.dist-info/RECORD
