Metadata-Version: 2.4
Name: pyrlib
Version: 0.0.1
Summary: A Python package for modular implementation of classical and deep Reinforcement Learning algorithms.
Author-email: Tyler Wallett <twallett@gwu.edu>
License: MIT
Classifier: Programming Language :: Python :: 3
Classifier: Operating System :: OS Independent
Requires-Python: >=3.8
Requires-Dist: requests
Requires-Dist: numpy
